readgssi/__init__.py
readgssi/_version.py
readgssi/arrayops.py
readgssi/config.py
readgssi/constants.py
readgssi/dzt.py
readgssi/dzx.py
readgssi/filtering.py
readgssi/functions.py
readgssi/gps.py
readgssi/plot.py
readgssi/readgssi.py
readgssi/translate.py
readgssi-0.0.22.dist-info/LICENSE
readgssi-0.0.22.dist-info/METADATA
readgssi-0.0.22.dist-info/WHEEL
readgssi-0.0.22.dist-info/entry_points.txt
readgssi-0.0.22.dist-info/top_level.txt
readgssi-0.0.22.dist-info/RECORD
