Metadata-Version: 2.1
Name: readgssi
Version: 0.0.22
Summary: Python tool to read and plot Geophysical Survey Systems Incorporated (GSSI) radar data in DZT format
Home-page: https://readgssi.readthedocs.org/
Author: Ian Nesbitt
Author-email: ian.nesbitt@gmail.com
License: AGPL
Classifier: Programming Language :: Python :: 3
Classifier: License :: OSI Approved :: GNU General Public License v3 (GPLv3)
Classifier: Operating System :: OS Independent
Classifier: Framework :: Matplotlib
Classifier: Topic :: Scientific/Engineering :: Physics
Classifier: Intended Audience :: Science/Research
Classifier: Natural Language :: English
Classifier: Development Status :: 4 - Beta
License-File: LICENSE
Requires-Dist: obspy
Requires-Dist: numpy
Requires-Dist: scipy
Requires-Dist: geopy
Requires-Dist: matplotlib
Requires-Dist: pandas
Requires-Dist: h5py
Requires-Dist: pynmea2
Requires-Dist: pytz
